pygecko/__init__.py
pygecko/file_storage.py
pygecko/gecko_enums.py
pygecko/messages.py
pygecko/msg_helpers.py
pygecko-1.3.0.data/scripts/gecko_log_display.py
pygecko-1.3.0.data/scripts/geckocore.py
pygecko-1.3.0.data/scripts/geckolaunch.py
pygecko-1.3.0.data/scripts/geckotopic.py
pygecko-1.3.0.data/scripts/pycore.py
pygecko-1.3.0.data/scripts/twist_keyboard.py
pygecko-1.3.0.dist-info/LICENSE
pygecko-1.3.0.dist-info/METADATA
pygecko-1.3.0.dist-info/WHEEL
pygecko-1.3.0.dist-info/top_level.txt
pygecko-1.3.0.dist-info/RECORD
