Metadata-Version: 2.1
Name: pygecko
Version: 1.3.0
Summary: A python robotic framework and tools
Home-page: https://github.com/MomsFriendlyRobotCompany/pygecko
Author: Kevin Walchko
Author-email: walchko@noreply.github.com
License: MIT
Keywords: framework,robotic,robot,vision,ros,distributed
Platform: UNKNOWN
Classifier: Development Status :: 4 - Beta
Classifier: License :: OSI Approved :: MIT License
Classifier: Programming Language :: Python :: 3.7
Classifier: Operating System :: Unix
Classifier: Operating System :: POSIX :: Linux
Classifier: Operating System :: MacOS :: MacOS X
Classifier: Operating System :: POSIX
Classifier: Topic :: Scientific/Engineering
Classifier: Topic :: Scientific/Engineering :: Artificial Intelligence
Classifier: Topic :: Scientific/Engineering :: Image Recognition
Classifier: Topic :: Software Development :: Libraries :: Python Modules
Requires-Dist: pyyaml
Requires-Dist: psutil
Requires-Dist: simplejson
Requires-Dist: msgpack
Requires-Dist: pyzmq
Requires-Dist: colorama
Requires-Dist: numpy
Requires-Dist: build-utils
